pybithumb2/__env__.py
pybithumb2/__init__.py
pybithumb2/client.py
pybithumb2/constants.py
pybithumb2/exceptions.py
pybithumb2/models.py
pybithumb2/rest.py
pybithumb2/stream.py
pybithumb2/types.py
pybithumb2/utils.py
pybithumb2-1.0.0b0.dist-info/licenses/LICENSE
pybithumb2-1.0.0b0.dist-info/METADATA
pybithumb2-1.0.0b0.dist-info/WHEEL
pybithumb2-1.0.0b0.dist-info/top_level.txt
pybithumb2-1.0.0b0.dist-info/RECORD
